{"hcad":{"acct":"1399450010031","site_address":"0 HUNTSFORD DR","site_address_norm":"0 HUNTSFORD DRIVE","zip_code":"77008","owner_name":"SULLIVAN BROTHERS BUILDERS LTD","state_class":"C1","school_dist":"01","neighborhood_code":"8301.18","neighborhood_grp":"1644","market_area_1":"160","market_area_1_dscr":"1F Lazybrook, Timbergrove, Washington Corridor","building_area":0.0,"land_area":717.0,"acreage":0.0165,"land_val":36.0,"bld_val":0.0,"x_features_val":0.0,"assessed_val":36.0,"tot_appr_val":36.0,"tot_mkt_val":36.0,"new_construction_val":0.0,"protested":"N","legal_description":"RES L BLK 1 (LANDSCAPE/OPEN SPACE/UTILITY) SEAMIST SEC 1"},"buildings":[],"ownership_history":[{"acct":"1399450010031","owner_name":"SULLIVAN BROTHERS BUILDERS LTD","site_address":"0 HUNTSFORD DR"}],"permits":[],"mls_listings":[],"valuation":null}