{"hcad":{"acct":"1247900010004","site_address":"1025 W 15TH 1/2 ST","site_address_norm":"1025 W 15TH 1/2 STREET","zip_code":"77008","owner_name":"CURRAN CONNER & RACHAEL M","state_class":"A1","school_dist":"01","neighborhood_code":"8303.12","neighborhood_grp":"1644","market_area_1":"160","market_area_1_dscr":"1F Lazybrook, Timbergrove, Washington Corridor","year_improved":2004,"building_area":1463.0,"land_area":3163.0,"acreage":0.0726,"land_val":173965.0,"bld_val":222926.0,"x_features_val":5882.0,"assessed_val":402773.0,"tot_appr_val":402773.0,"tot_mkt_val":402773.0,"new_construction_val":0.0,"protested":"N","legal_description":"LT 4 BLK 1 SHADY PARK COTTAGES"},"buildings":[{"acct":"1247900010004","bld_num":1,"property_use_cd":"A1","structure_desc":"Residential","year_built":2004,"effective_year":2004,"im_sq_ft":1463.0,"act_ar":1680.0,"gross_ar":1680.0,"base_ar":1463.0}],"ownership_history":[{"acct":"1247900010004","owner_name":"CURRAN CONNER & RACHAEL M","site_address":"1025 W 15TH 1/2 ST"}],"permits":[{"acct":"1247900010004","status":"C","description":"NEW DWG","permit_type":"09","permit_type_desc":"New Dwelling - no permit","yr":2005}],"mls_listings":[{"mls_number":"80289789","status":"Sold","property_type":"Single-Family","list_price":390000.0,"close_price":390000.0,"list_date":"2021-10-22","close_date":"2021-11-23","dom":7,"cdom":7,"bedrooms":3,"baths_full":2,"baths_half":1,"building_sqft":1463.0,"year_built":2004}],"valuation":{"method":"ZHVI-adjusted MLS comps","window_months":12,"sqft_band_pct":25,"lot_band_applied":true,"year_band_applied":true,"sqft_used":1463,"comp_count":13,"ppsf_low":244,"ppsf_mid":278,"ppsf_high":308,"est_low":357393,"est_mid":407062,"est_high":450853,"zhvi_as_of":"2026-04-30"}}