{"hcad":{"acct":"0350870340004","site_address":"108 E 27TH ST","site_address_norm":"108 E 27TH ST","zip_code":"77008","state_class":"A1","school_dist":"01","neighborhood_code":"8305.00","neighborhood_grp":"1640","market_area_1":"161","market_area_1_dscr":"1F Heights, Brooksmith, Norhill Areas","year_improved":1920,"building_area":912.0,"land_area":4500.0,"acreage":0.1033,"land_val":382500.0,"bld_val":194793.0,"x_features_val":1937.0,"assessed_val":579230.0,"tot_appr_val":576400.0,"tot_mkt_val":579230.0,"new_construction_val":0.0,"protested":"Y","legal_description":"LT 5 & TR 4 BLK 34 SUNSET HEIGHTS"},"buildings":[{"acct":"0350870340004","bld_num":1,"property_use_cd":"A1","structure_desc":"Residential","year_built":1920,"effective_year":1920,"year_remodeled":2016,"im_sq_ft":912.0,"act_ar":960.0,"gross_ar":960.0,"base_ar":912.0}],"ownership_history":[],"permits":[{"acct":"0350870340004","status":"C","description":"RESIDENTIAL REMODEL AND REPAIRS.","permit_type":"11","permit_type_desc":"Additions or Remodeling","yr":2018}],"mls_listings":[{"mls_number":"56463507","status":"Sold","property_type":"Single-Family","list_price":475000.0,"close_price":485000.0,"list_date":"2021-08-08","close_date":"2021-09-10","dom":10,"cdom":10,"bedrooms":2,"baths_full":2,"baths_half":0,"building_sqft":925.0,"year_built":1920}],"valuation":{"method":"ZHVI-adjusted MLS comps","window_months":30,"sqft_band_pct":25,"year_band_applied":true,"sqft_used":912,"comp_count":51,"ppsf_low":482,"ppsf_mid":558,"ppsf_high":582,"est_low":439984,"est_mid":508946,"est_high":530713,"zhvi_as_of":"2026-04-30"}}