{"hcad":{"acct":"0440820000166","site_address":"1350 BEALL ST","site_address_norm":"1350 BEALL STREET","zip_code":"77008","owner_name":"NICKELL SCOTT L","state_class":"A1","school_dist":"01","neighborhood_code":"8303.12","neighborhood_grp":"1644","market_area_1":"160","market_area_1_dscr":"1F Lazybrook, Timbergrove, Washington Corridor","year_improved":2002,"building_area":1574.0,"land_area":4741.0,"acreage":0.1088,"land_val":260755.0,"bld_val":217766.0,"x_features_val":20107.0,"assessed_val":498628.0,"tot_appr_val":498628.0,"tot_mkt_val":498628.0,"new_construction_val":0.0,"protested":"Y","legal_description":"TR 12S ABST 642 J REINERMAN"},"buildings":[{"acct":"0440820000166","bld_num":2,"property_use_cd":"A1","structure_desc":"Residential","year_built":2002,"effective_year":2002,"im_sq_ft":1574.0,"act_ar":1650.0,"gross_ar":1650.0,"base_ar":1574.0}],"ownership_history":[{"acct":"0440820000166","owner_name":"NICKELL SCOTT L","site_address":"1350 BEALL ST"}],"permits":[{"acct":"0440820000166","status":"C","description":"O/P","permit_type":"15","permit_type_desc":"Relocation / Bldg Move","yr":2009}],"mls_listings":[],"valuation":{"method":"ZHVI-adjusted MLS comps","window_months":12,"sqft_band_pct":25,"lot_band_applied":true,"year_band_applied":true,"sqft_used":1574,"comp_count":9,"ppsf_low":252,"ppsf_mid":335,"ppsf_high":370,"est_low":396762,"est_mid":527271,"est_high":582877,"spread_pct":35,"confidence":"low","zhvi_as_of":"2026-04-30"}}