{"hcad":{"acct":"1412860010013","site_address":"1403 BIONDO WAY","site_address_norm":"1403 BIONDO WAY","zip_code":"77008","owner_name":"WITHERS PATRICK C % WITHERS FAMILY TRUST","state_class":"A1","school_dist":"01","neighborhood_code":"8301.17","neighborhood_grp":"1644","market_area_1":"160","market_area_1_dscr":"1F Lazybrook, Timbergrove, Washington Corridor","year_improved":2021,"building_area":2162.0,"land_area":2934.0,"acreage":0.0673,"land_val":172690.0,"bld_val":457373.0,"x_features_val":0.0,"assessed_val":630063.0,"tot_appr_val":630063.0,"tot_mkt_val":630063.0,"new_construction_val":0.0,"protested":"Y","legal_description":"LT 13 BLK 1 ESTATES AT MINIMAX"},"buildings":[{"acct":"1412860010013","bld_num":1,"property_use_cd":"A1","structure_desc":"Residential","year_built":2021,"effective_year":2021,"im_sq_ft":2162.0,"act_ar":2638.0,"gross_ar":2638.0,"base_ar":2162.0}],"ownership_history":[{"acct":"1412860010013","owner_name":"WITHERS PATRICK C","site_address":"1403 BIONDO WAY"}],"permits":[{"acct":"1412860010013","status":"C","description":"S.F. RESIDENCE W/ATTACHED GARAGE (1-2-5-R3-B) 12 I","permit_type":"10","permit_type_desc":"New Dwelling - permit","yr":2022}],"mls_listings":[],"valuation":{"method":"ZHVI-adjusted MLS comps","window_months":12,"sqft_band_pct":25,"lot_band_applied":true,"year_band_applied":true,"sqft_used":2162,"comp_count":170,"ppsf_low":210,"ppsf_mid":235,"ppsf_high":277,"est_low":454972,"est_mid":508958,"est_high":599761,"spread_pct":28,"confidence":"medium","zhvi_as_of":"2026-04-30"}}