{"hcad":{"acct":"0201470000014","site_address":"1411 ASHLAND ST","site_address_norm":"1411 ASHLAND STREET","zip_code":"77008","owner_name":"CHEN PAULA P","state_class":"A1","school_dist":"01","neighborhood_code":"8304.06","neighborhood_grp":"1620","market_area_1":"161","market_area_1_dscr":"1F Heights, Brooksmith, Norhill Areas","year_improved":2015,"building_area":3820.0,"land_area":6600.0,"acreage":0.1515,"land_val":594000.0,"bld_val":1222617.0,"x_features_val":0.0,"assessed_val":1816617.0,"tot_appr_val":1816617.0,"tot_mkt_val":1816617.0,"new_construction_val":0.0,"protested":"N","legal_description":"LT 15 & TR 14 BLK 151 HOUSTON HEIGHTS"},"buildings":[{"acct":"0201470000014","bld_num":1,"property_use_cd":"A1","structure_desc":"Residential","year_built":2015,"effective_year":2015,"im_sq_ft":3820.0,"act_ar":5266.0,"gross_ar":5266.0,"base_ar":3820.0}],"ownership_history":[{"acct":"0201470000014","owner_name":"CHEN PAULA P","site_address":"1411 ASHLAND ST"}],"permits":[{"acct":"0201470000014","status":"C","description":"HCHA - MINOR","permit_type":"50","permit_type_desc":"Disaster Review","yr":2009},{"acct":"0201470000014","status":"C","description":"DEMO RES/SEWER DISC","permit_type":"13","permit_type_desc":"Residential Demolition","yr":2015},{"acct":"0201470000014","status":"C","description":"2 STORY S.F. RES W/ ATT GAR (1-2-5-R3-B) 06 IRC","permit_type":"10","permit_type_desc":"New Dwelling - permit","yr":2017}],"mls_listings":[],"valuation":{"method":"ZHVI-adjusted MLS comps","window_months":12,"sqft_band_pct":25,"lot_band_applied":true,"year_band_applied":true,"sqft_used":3820,"comp_count":64,"ppsf_low":338,"ppsf_mid":391,"ppsf_high":440,"est_low":1290356,"est_mid":1492690,"est_high":1681815,"spread_pct":26,"confidence":"medium","zhvi_as_of":"2026-04-30"}}