{"hcad":{"acct":"0142580000024","site_address":"1521 OVID ST","site_address_norm":"1521 OVID ST","zip_code":"77007","state_class":"A1","school_dist":"01","neighborhood_code":"8311.00","neighborhood_grp":"1652","market_area_1":"160","market_area_1_dscr":"1F Lazybrook, Timbergrove, Washington Corridor","year_improved":2025,"building_area":2930.0,"land_area":4960.0,"acreage":0.1139,"land_val":322400.0,"bld_val":658935.0,"x_features_val":0.0,"assessed_val":981335.0,"tot_appr_val":981335.0,"tot_mkt_val":981335.0,"new_construction_val":658935.0,"protested":"Y","legal_description":"TRS 1 & 2 BLK 4 FRITZ"},"buildings":[{"acct":"0142580000024","bld_num":1,"property_use_cd":"A1","structure_desc":"Residential","year_built":2025,"effective_year":2025,"im_sq_ft":2930.0,"act_ar":3758.0,"gross_ar":3758.0,"base_ar":2930.0}],"ownership_history":[],"permits":[{"acct":"0142580000024","status":"C","description":"S.F. RES W/ATT. GARAGE (1-2-5-R3-B) 21 IRC/21 IECC","permit_type":"10","permit_type_desc":"New Dwelling - permit","yr":2026}],"mls_listings":[]}