{"hcad":{"acct":"0201390000042","site_address":"1532 RUTLAND ST","site_address_norm":"1532 RUTLAND STREET","zip_code":"77008","state_class":"A1","school_dist":"01","neighborhood_code":"8304.06","neighborhood_grp":"1620","market_area_1":"161","market_area_1_dscr":"1F Heights, Brooksmith, Norhill Areas","year_improved":1999,"building_area":2949.0,"land_area":4840.0,"acreage":0.1111,"land_val":435600.0,"bld_val":620240.0,"x_features_val":7149.0,"assessed_val":1062989.0,"tot_appr_val":1062989.0,"tot_mkt_val":1062989.0,"new_construction_val":0.0,"protested":"N","legal_description":"TRS 29 & 30A BLK 143 HOUSTON HEIGHTS"},"buildings":[{"acct":"0201390000042","bld_num":1,"property_use_cd":"A1","structure_desc":"Residential","year_built":1999,"effective_year":1999,"im_sq_ft":2949.0,"act_ar":3400.0,"gross_ar":3400.0,"base_ar":2949.0}],"ownership_history":[],"permits":[],"mls_listings":[],"valuation":{"method":"ZHVI-adjusted MLS comps","window_months":12,"sqft_band_pct":25,"lot_band_applied":true,"year_band_applied":true,"sqft_used":2949,"comp_count":153,"ppsf_low":266,"ppsf_mid":334,"ppsf_high":395,"est_low":785033,"est_mid":984270,"est_high":1164816,"zhvi_as_of":"2026-04-30"}}