{"hcad":{"acct":"0201100000036","site_address":"1603 COLUMBIA ST","site_address_norm":"1603 COLUMBIA ST","zip_code":"77008","state_class":"A1","school_dist":"01","neighborhood_code":"8304.02","neighborhood_grp":"1617","market_area_1":"161","market_area_1_dscr":"1F Heights, Brooksmith, Norhill Areas","year_improved":2005,"building_area":2352.0,"land_area":4488.0,"acreage":0.103,"land_val":403920.0,"bld_val":596300.0,"x_features_val":10227.0,"assessed_val":1010447.0,"tot_appr_val":1010447.0,"tot_mkt_val":1010447.0,"new_construction_val":0.0,"protested":"N","legal_description":"LT 12A HOUSTON HEIGHTS 35TH AMEND"},"buildings":[{"acct":"0201100000036","bld_num":1,"property_use_cd":"A1","structure_desc":"Residential","year_built":2005,"effective_year":2005,"im_sq_ft":2352.0,"act_ar":2856.0,"gross_ar":2856.0,"base_ar":2352.0}],"ownership_history":[],"permits":[{"acct":"0201100000036","status":"C","description":"DWG","permit_type":"09","permit_type_desc":"New Dwelling - no permit","yr":2006}],"mls_listings":[{"mls_number":"61663642","status":"Sold","property_type":"Single-Family","list_price":1150000.0,"close_price":1165000.0,"list_date":"2025-07-10","close_date":"2025-08-07","dom":3,"cdom":3,"bedrooms":3,"baths_full":3,"baths_half":0,"building_sqft":2352.0,"year_built":2005}],"valuation":{"method":"ZHVI-adjusted MLS comps","window_months":12,"sqft_band_pct":25,"lot_band_applied":true,"year_band_applied":true,"sqft_used":2352,"comp_count":154,"ppsf_low":264,"ppsf_mid":298,"ppsf_high":343,"est_low":620582,"est_mid":701393,"est_high":807278,"zhvi_as_of":"2026-04-30"}}