{"hcad":{"acct":"0311010000004","site_address":"1605 MALVERN ST","site_address_norm":"1605 MALVERN STREET","zip_code":"77009","owner_name":"GREER NADIE NAPOLEON","state_class":"A1","school_dist":"01","neighborhood_code":"7052.00","neighborhood_grp":"1541","market_area_1":"150","market_area_1_dscr":"1E Ryon, Irvington, Lindale Areas","year_improved":1940,"building_area":539.0,"land_area":5000.0,"acreage":0.1148,"land_val":138000.0,"bld_val":19358.0,"x_features_val":0.0,"assessed_val":157358.0,"tot_appr_val":157358.0,"tot_mkt_val":157358.0,"new_construction_val":0.0,"protested":"N","legal_description":"TRS 4A & 5A BLK 101 RYON"},"buildings":[{"acct":"0311010000004","bld_num":1,"property_use_cd":"A1","structure_desc":"Residential","year_built":1940,"effective_year":1940,"im_sq_ft":539.0,"act_ar":594.0,"gross_ar":594.0,"base_ar":539.0}],"ownership_history":[{"acct":"0311010000004","owner_name":"GREER NADIE NAPOLEON","site_address":"1605 MALVERN ST"}],"permits":[],"mls_listings":[],"valuation":{"method":"segment-adjusted MLS comps","window_months":12,"sqft_band_pct":25,"lot_band_applied":false,"year_band_applied":false,"sqft_used":539,"comp_count":4,"ppsf_low":223,"ppsf_mid":244,"ppsf_high":299,"est_low":119987,"est_mid":131323,"est_high":160957,"spread_pct":31,"confidence":"medium","index_as_of":"2026-04-01"}}