{"hcad":{"acct":"0051220000004","site_address":"1708 CROCKETT ST","site_address_norm":"1708 CROCKETT STREET","zip_code":"77007","owner_name":"MERRIFIELD KATE E","state_class":"A1","school_dist":"01","neighborhood_code":"8311.00","neighborhood_grp":"1652","market_area_1":"160","market_area_1_dscr":"1F Lazybrook, Timbergrove, Washington Corridor","year_improved":1930,"building_area":1156.0,"land_area":5000.0,"acreage":0.1148,"land_val":325000.0,"bld_val":142553.0,"x_features_val":0.0,"assessed_val":467553.0,"tot_appr_val":467553.0,"tot_mkt_val":467553.0,"new_construction_val":0.0,"protested":"N","legal_description":"LT 4 BLK 299 BAKER NSBB"},"buildings":[{"acct":"0051220000004","bld_num":1,"property_use_cd":"A1","structure_desc":"Residential","year_built":1930,"effective_year":1930,"year_remodeled":2018,"im_sq_ft":1156.0,"act_ar":1353.0,"gross_ar":1353.0,"base_ar":1156.0}],"ownership_history":[{"acct":"0051220000004","owner_name":"MERRIFIELD KATE E","site_address":"1708 CROCKETT ST"}],"permits":[],"mls_listings":[{"mls_number":"22184640","status":"Sold","property_type":"Single-Family","list_price":495000.0,"close_price":481000.0,"list_date":"2021-08-17","close_date":"2021-09-20","dom":4,"cdom":4,"bedrooms":2,"baths_full":1,"baths_half":1,"building_sqft":1156.0,"year_built":1930}],"valuation":{"method":"ZHVI-adjusted MLS comps","window_months":12,"sqft_band_pct":15,"lot_band_applied":true,"year_band_applied":true,"sqft_used":1156,"comp_count":12,"ppsf_low":369,"ppsf_mid":437,"ppsf_high":476,"est_low":426013,"est_mid":505742,"est_high":549714,"zhvi_as_of":"2026-04-30"}}