{"hcad":{"acct":"0070290000003","site_address":"1710 ALAMO ST","site_address_norm":"1710 ALAMO ST","zip_code":"77007","state_class":"A1","school_dist":"01","neighborhood_code":"8311.00","neighborhood_grp":"1652","market_area_1":"160","market_area_1_dscr":"1F Lazybrook, Timbergrove, Washington Corridor","year_improved":1910,"building_area":900.0,"land_area":5000.0,"acreage":0.1148,"land_val":325000.0,"bld_val":21469.0,"x_features_val":1586.0,"assessed_val":348055.0,"tot_appr_val":348055.0,"tot_mkt_val":348055.0,"new_construction_val":0.0,"protested":"N","legal_description":"LT 3 BLK 24 BEAUCHAMP SPRINGS"},"buildings":[{"acct":"0070290000003","bld_num":1,"property_use_cd":"A1","structure_desc":"Residential","year_built":1910,"effective_year":1910,"im_sq_ft":900.0,"act_ar":1023.0,"gross_ar":1023.0,"base_ar":900.0}],"ownership_history":[],"permits":[{"acct":"0070290000003","status":"C","description":"COH - MINOR","permit_type":"50","permit_type_desc":"Disaster Review","yr":2009}],"mls_listings":[],"valuation":{"method":"ZHVI-adjusted MLS comps","window_months":30,"sqft_band_pct":25,"lot_band_applied":true,"year_band_applied":true,"sqft_used":900,"comp_count":22,"ppsf_low":370,"ppsf_mid":471,"ppsf_high":538,"est_low":333392,"est_mid":423824,"est_high":484207,"zhvi_as_of":"2026-04-30"}}