{"hcad":{"acct":"1242020010001","site_address":"1718 W 26TH ST","site_address_norm":"1718 W 26TH STREET","zip_code":"77008","owner_name":"ALATE REAL ESTATE LLC","state_class":"F1","school_dist":"01","neighborhood_code":"5938.27","neighborhood_grp":"0","market_area_1":"6004","market_area_1_dscr":"Inner Loop North","year_improved":1988,"building_area":21202.0,"land_area":54446.0,"acreage":1.2499,"land_val":3266760.0,"bld_val":262922.0,"x_features_val":0.0,"assessed_val":3529682.0,"tot_appr_val":3529682.0,"tot_mkt_val":3529682.0,"new_construction_val":0.0,"protested":"Y","legal_description":"RES A BLK 1 EXCELL"},"buildings":[],"ownership_history":[{"acct":"1242020010001","owner_name":"ALATE REAL ESTATE LLC","site_address":"1718 W 26TH ST"}],"permits":[{"acct":"1242020010001","status":"C","description":"CONVERSION, WAREHOUSE","permit_type":"30","permit_type_desc":"New Building","yr":2020}],"mls_listings":[],"valuation":null}