{"hcad":{"acct":"1297120050003","site_address":"2110 SHEARN ST 29","site_address_norm":"2110 SHEARN ST 29","zip_code":"77007","state_class":"Z3","school_dist":"01","neighborhood_code":"5394.07","neighborhood_grp":"1801","market_area_1":"192","market_area_1_dscr":"1H Condo - Heights/I-10 Corridor","year_improved":2008,"building_area":1403.0,"land_area":0.0,"acreage":0.0,"land_val":71776.0,"bld_val":305990.0,"x_features_val":0.0,"assessed_val":377766.0,"tot_appr_val":377766.0,"tot_mkt_val":377766.0,"new_construction_val":0.0,"protested":"N","legal_description":"UNIT 29 BLDG B .0222 INT COMMON LAND & ELE SAWYER BROWNSTONES CONDO 3RD AMEND"},"buildings":[{"acct":"1297120050003","bld_num":1,"property_use_cd":"Z3","structure_desc":"Residential","year_built":2008,"effective_year":2008,"im_sq_ft":1403.0,"act_ar":1872.0,"gross_ar":1872.0,"base_ar":1403.0}],"ownership_history":[],"permits":[{"acct":"1297120050003","status":"C","description":"NEW CONDO","permit_type":"20","permit_type_desc":"New Condominium Unit","yr":2011}],"mls_listings":[],"valuation":{"method":"ZHVI-adjusted MLS comps","window_months":30,"sqft_band_pct":25,"year_band_applied":true,"sqft_used":1403,"comp_count":153,"ppsf_low":217,"ppsf_mid":241,"ppsf_high":269,"est_low":304865,"est_mid":338101,"est_high":377855,"zhvi_as_of":"2026-04-30"}}