{"hcad":{"acct":"0440820000713","site_address":"2122 W 11TH ST","site_address_norm":"2122 W 11TH STREET","zip_code":"77008","owner_name":"CITY OF HOUSTON","state_class":"X1","school_dist":"01","neighborhood_code":"5950.00","neighborhood_grp":"0","market_area_1":"4008","market_area_1_dscr":"Brookhollow","building_area":0.0,"land_area":1087741.0,"acreage":24.9711,"land_val":0.0,"bld_val":0.0,"x_features_val":0.0,"assessed_val":0.0,"tot_appr_val":0.0,"tot_mkt_val":0.0,"new_construction_val":0.0,"protested":"N","legal_description":"TRS 40L 41B 41C & 41E ABST 642 J REINERMAN"},"buildings":[],"ownership_history":[{"acct":"0440820000713","owner_name":"CITY OF HOUSTON","site_address":"2122 W 11TH ST"}],"permits":[{"acct":"0440820000713","status":"C","description":"NEW ODOR CONTROL EQMT","permit_type":"84","permit_type_desc":"Exempt Property","yr":2008},{"acct":"0440820000713","status":"C","description":"FIRELOSS#2408180101/RES ST RD OR DRIVEWAY","permit_type":"84","permit_type_desc":"Exempt Property","yr":2025},{"acct":"0440820000713","status":"C","description":"NEW ODOR CONTROL SYSTEM","permit_type":"31","permit_type_desc":"Addtns, Remodels, Lease Space","yr":2015},{"acct":"0440820000713","status":"C","description":"PARK IMPROVEMENTS SIDEWALK/DRIVEWAY","permit_type":"31","permit_type_desc":"Addtns, Remodels, Lease Space","yr":2015}],"mls_listings":[],"valuation":null}