{"hcad":{"acct":"0200240000011","site_address":"224 W 27TH ST","site_address_norm":"224 W 27TH STREET","zip_code":"77008","owner_name":"JACOBS GLENN L III","state_class":"A1","school_dist":"01","neighborhood_code":"8304.00","neighborhood_grp":"1639","market_area_1":"161","market_area_1_dscr":"1F Heights, Brooksmith, Norhill Areas","year_improved":1942,"building_area":796.0,"land_area":6550.0,"acreage":0.1504,"land_val":622250.0,"bld_val":32857.0,"x_features_val":242.0,"assessed_val":655349.0,"tot_appr_val":582931.0,"tot_mkt_val":655349.0,"new_construction_val":0.0,"protested":"N","legal_description":"LTS 11 & 12 BLK 28 HOUSTON HEIGHTS"},"buildings":[{"acct":"0200240000011","bld_num":1,"property_use_cd":"A1","structure_desc":"Residential","year_built":1942,"effective_year":1942,"im_sq_ft":796.0,"act_ar":1102.0,"gross_ar":1102.0,"base_ar":796.0}],"ownership_history":[{"acct":"0200240000011","owner_name":"JACOBS GLENN L III","site_address":"224 W 27TH ST"}],"permits":[],"mls_listings":[],"valuation":{"method":"segment-adjusted MLS comps","window_months":12,"sqft_band_pct":25,"lot_band_applied":true,"year_band_applied":true,"sqft_used":796,"comp_count":5,"ppsf_low":486,"ppsf_mid":563,"ppsf_high":567,"est_low":386570,"est_mid":448198,"est_high":451555,"spread_pct":14,"confidence":"high","index_as_of":"2026-04-01"}}