{"hcad":{"acct":"0350830260027","site_address":"2601 BAYLOR ST","site_address_norm":"2601 BAYLOR STREET","zip_code":"77009","owner_name":"CROSSBELL VENTURES REAL PROPERTY LLC","state_class":"F1","school_dist":"01","neighborhood_code":"5938.07","neighborhood_grp":"0","market_area_1":"5020","market_area_1_dscr":"Heights","year_improved":1930,"building_area":1721.0,"land_area":5880.0,"acreage":0.135,"land_val":441000.0,"bld_val":90707.0,"x_features_val":14694.0,"assessed_val":546401.0,"tot_appr_val":546401.0,"tot_mkt_val":546401.0,"new_construction_val":0.0,"protested":"Y","legal_description":"LTS 27 & 28 BLK 26 SUNSET HEIGHTS"},"buildings":[],"ownership_history":[{"acct":"0350830260027","owner_name":"CROSSBELL VENTURES REAL PROPERTY LLC","site_address":"2601 BAYLOR ST"}],"permits":[{"acct":"0350830260027","status":"C","description":"HCHA - MAJOR","permit_type":"50","permit_type_desc":"Disaster Review","yr":2011},{"acct":"0350830260027","status":"C","description":"RESIDENTIAL REPAIR PER SPEC LIST","permit_type":"11","permit_type_desc":"Additions or Remodeling","yr":2022}],"mls_listings":[{"mls_number":"21553538","status":"Sold","property_type":"Single-Family","list_price":349687.0,"close_price":340000.0,"list_date":"2019-03-21","close_date":"2019-05-13","dom":8,"cdom":147,"bedrooms":0,"baths_full":2,"baths_half":0,"building_sqft":1619.0,"year_built":1930}],"valuation":{"method":"ZHVI-adjusted MLS comps","window_months":12,"sqft_band_pct":25,"lot_band_applied":true,"year_band_applied":true,"sqft_used":1721,"comp_count":123,"ppsf_low":254,"ppsf_mid":377,"ppsf_high":498,"est_low":437212,"est_mid":649408,"est_high":856468,"zhvi_as_of":"2026-04-30"}}