{"hcad":{"acct":"0310050000005","site_address":"2702 HARDY ST","site_address_norm":"2702 HARDY ST","zip_code":"77009","state_class":"A1","school_dist":"01","neighborhood_code":"7080.02","neighborhood_grp":"1542","market_area_1":"150","market_area_1_dscr":"1E Ryon, Irvington, Lindale Areas","year_improved":1953,"building_area":920.0,"land_area":4150.0,"acreage":0.0953,"land_val":189365.0,"bld_val":32458.0,"x_features_val":0.0,"assessed_val":221823.0,"tot_appr_val":116132.0,"tot_mkt_val":221823.0,"new_construction_val":0.0,"protested":"N","legal_description":"TR 5 BLK 5 RYON"},"buildings":[{"acct":"0310050000005","bld_num":1,"property_use_cd":"A1","structure_desc":"Residential","year_built":1953,"effective_year":1953,"im_sq_ft":920.0,"act_ar":980.0,"gross_ar":980.0,"base_ar":920.0}],"ownership_history":[],"permits":[],"mls_listings":[],"valuation":{"method":"ZHVI-adjusted MLS comps","window_months":12,"sqft_band_pct":25,"lot_band_applied":true,"year_band_applied":true,"sqft_used":920,"comp_count":23,"ppsf_low":194,"ppsf_mid":269,"ppsf_high":382,"est_low":178090,"est_mid":247088,"est_high":351232,"zhvi_as_of":"2026-04-30"}}