{"hcad":{"acct":"1401380020001","site_address":"2795 KATY FWY","site_address_norm":"2795 KATY FWY","zip_code":"77007","state_class":"F1","school_dist":"01","neighborhood_code":"5924.00","neighborhood_grp":"0","market_area_1":"5020","market_area_1_dscr":"Heights","year_improved":2022,"building_area":33010.0,"land_area":114894.0,"acreage":2.6376,"land_val":1536660.0,"bld_val":12700626.0,"x_features_val":0.0,"assessed_val":14237286.0,"tot_appr_val":14237286.0,"tot_mkt_val":14237286.0,"new_construction_val":0.0,"protested":"Y","legal_description":"RES A BLK 1 LOWER HEIGHTS DISTRICT R/P"},"buildings":[],"ownership_history":[],"permits":[{"acct":"1401380020001","status":"C","description":"NEW FOUNDATION ONLY FOR PARKING GARAGE","permit_type":"31","permit_type_desc":"Addtns, Remodels, Lease Space","yr":2021},{"acct":"1401380020001","status":"C","description":"NEW COMMERCIAL SHELL BUILDING","permit_type":"30","permit_type_desc":"New Building","yr":2021},{"acct":"1401380020001","status":"C","description":"2,700 SQ FT RETAIL BUILD OUT 1-1-2-M-B '15 IBC","permit_type":"31","permit_type_desc":"Addtns, Remodels, Lease Space","yr":2024},{"acct":"1401380020001","status":"C","description":"BUILDOUT, RESTAURANT","permit_type":"30","permit_type_desc":"New Building","yr":2024},{"acct":"1401380020001","status":"C","description":"1,237 SF BEAUTY SALON BUILDOUT 1-2-2-B-B 2015 IBC","permit_type":"31","permit_type_desc":"Addtns, Remodels, Lease Space","yr":2024},{"acct":"1401380020001","status":"C","description":"1,801 SF RESTAURANT BUILDOUT  1-1-2-B-B-SPK/FA '15","permit_type":"31","permit_type_desc":"Addtns, Remodels, Lease Space","yr":2025},{"acct":"1401380020001","status":"C","description":"2,208 S.F. RESTURANT BUILDOUT  1-1-2-A2-B '21 IBC","permit_type":"31","permit_type_desc":"Addtns, Remodels, Lease Space","yr":2025},{"acct":"1401380020001","status":"C","description":"929 SF. SPEC LEASE BUILDOUT 1-2-2-B-B '21 IBC","permit_type":"31","permit_type_desc":"Addtns, Remodels, Lease Space","yr":2026},{"acct":"1401380020001","status":"C","description":"1,216 SF. SPEC LEASE BUILDOUT 1-2-2-B-B '21 IBC","permit_type":"31","permit_type_desc":"Addtns, Remodels, Lease Space","yr":2026}],"mls_listings":[]}