{"hcad":{"acct":"0300650000052","site_address":"304 MALONE ST","site_address_norm":"304 MALONE STREET","zip_code":"77007","owner_name":"CURRENT OWNER","state_class":"A1","school_dist":"01","neighborhood_code":"8307.05","neighborhood_grp":"1623","market_area_1":"160","market_area_1_dscr":"1F Lazybrook, Timbergrove, Washington Corridor","year_improved":2016,"building_area":3890.0,"land_area":2875.0,"acreage":0.066,"land_val":255313.0,"bld_val":702512.0,"x_features_val":6716.0,"assessed_val":964541.0,"tot_appr_val":964541.0,"tot_mkt_val":964541.0,"new_construction_val":0.0,"protested":"N","legal_description":"LT 32 BLK 23 RICE MILITARY"},"buildings":[{"acct":"0300650000052","bld_num":1,"property_use_cd":"A1","structure_desc":"Residential","year_built":2016,"effective_year":2016,"im_sq_ft":3890.0,"act_ar":4843.0,"gross_ar":4843.0,"base_ar":3890.0}],"ownership_history":[{"acct":"0300650000052","owner_name":"CURRENT OWNER","site_address":"304 MALONE ST"}],"permits":[],"mls_listings":[],"valuation":{"method":"ZHVI-adjusted MLS comps","window_months":12,"sqft_band_pct":25,"lot_band_applied":true,"year_band_applied":true,"sqft_used":3890,"comp_count":65,"ppsf_low":216,"ppsf_mid":237,"ppsf_high":280,"est_low":840485,"est_mid":922643,"est_high":1089221,"spread_pct":27,"confidence":"medium","zhvi_as_of":"2026-04-30"}}