{"hcad":{"acct":"0400680000022","site_address":"316 RAILEY ST","site_address_norm":"316 RAILEY STREET","zip_code":"77009","owner_name":"ZERSEN SCOTT G","state_class":"C1","school_dist":"01","neighborhood_code":"8306.01","neighborhood_grp":"1641","market_area_1":"161","market_area_1_dscr":"1F Heights, Brooksmith, Norhill Areas","building_area":0.0,"land_area":6300.0,"acreage":0.1446,"land_val":368550.0,"bld_val":0.0,"x_features_val":0.0,"assessed_val":368550.0,"tot_appr_val":120000.0,"tot_mkt_val":368550.0,"new_construction_val":0.0,"protested":"N","legal_description":"TR 22 BRINGHURST/RAMSEY TR U/R ABST 1 J AUSTIN"},"buildings":[],"ownership_history":[{"acct":"0400680000022","owner_name":"ZERSEN SCOTT G","site_address":"316 RAILEY ST"}],"permits":[],"mls_listings":[],"valuation":null}