{"hcad":{"acct":"0580050020012","site_address":"3416 NORTHWOOD ST","site_address_norm":"3416 NORTHWOOD STREET","zip_code":"77009","owner_name":"MAJOIE MARLENA A","state_class":"A1","school_dist":"01","neighborhood_code":"8305.14","neighborhood_grp":"1644","market_area_1":"161","market_area_1_dscr":"1F Heights, Brooksmith, Norhill Areas","year_improved":1985,"building_area":1251.0,"land_area":1245.0,"acreage":0.0286,"land_val":124500.0,"bld_val":201130.0,"x_features_val":0.0,"assessed_val":325630.0,"tot_appr_val":325630.0,"tot_mkt_val":325630.0,"new_construction_val":0.0,"protested":"Y","legal_description":"LT 3 BLK A HERMOSA COURT"},"buildings":[{"acct":"0580050020012","bld_num":1,"property_use_cd":"A1","structure_desc":"Residential","year_built":1985,"effective_year":1985,"year_remodeled":2008,"im_sq_ft":1251.0,"act_ar":1800.0,"gross_ar":1800.0,"base_ar":1251.0}],"ownership_history":[{"acct":"0580050020012","owner_name":"MAJOIE MARLENA A","site_address":"3416 NORTHWOOD ST"}],"permits":[{"acct":"0580050020012","status":"C","description":"TOWNHOME EXTERIOR REPAIR 1-2-5-R3-B 2006 IRC","permit_type":"12","permit_type_desc":"Repairs (Foundation / GM)","yr":2012}],"mls_listings":[],"valuation":{"method":"segment-adjusted MLS comps","window_months":12,"sqft_band_pct":25,"lot_band_applied":true,"year_band_applied":false,"sqft_used":1251,"comp_count":5,"ppsf_low":207,"ppsf_mid":215,"ppsf_high":224,"est_low":259414,"est_mid":268700,"est_high":280638,"spread_pct":8,"confidence":"high","index_as_of":"2026-04-01"}}