{"hcad":{"acct":"0201030000025","site_address":"402 E 20TH ST","site_address_norm":"402 E 20TH ST","zip_code":"77008","state_class":"F1","school_dist":"01","neighborhood_code":"5938.13","neighborhood_grp":"0","market_area_1":"5020","market_area_1_dscr":"Heights","year_improved":1950,"building_area":3264.0,"land_area":11220.0,"acreage":0.2576,"land_val":1009800.0,"bld_val":227004.0,"x_features_val":36292.0,"assessed_val":1273096.0,"tot_appr_val":1273096.0,"tot_mkt_val":1273096.0,"new_construction_val":54482.0,"protested":"Y","legal_description":"LT 26 & TR 25 BLK 107 HOUSTON HEIGHTS"},"buildings":[],"ownership_history":[],"permits":[{"acct":"0201030000025","status":"C","description":"COMMERCIAL REPAIRS PER SPEC LIST 2015 IRC","permit_type":"31","permit_type_desc":"Addtns, Remodels, Lease Space","yr":2024},{"acct":"0201030000025","status":"M","description":"CONVERSION, RESTAURANT","permit_type":"30","permit_type_desc":"New Building","yr":2027},{"acct":"0201030000025","status":"C","description":"2,891 SF CONV'T UPHOLSTERY TO RESTAURANT 1-1-5-A2-","permit_type":"31","permit_type_desc":"Addtns, Remodels, Lease Space","yr":2024}],"mls_listings":[]}