{"hcad":{"acct":"0211770480017","site_address":"4023 EDISON ST","site_address_norm":"4023 EDISON STREET","zip_code":"77009","owner_name":"PUENTE ROLAND","state_class":"A1","school_dist":"01","neighborhood_code":"7050.00","neighborhood_grp":"1541","market_area_1":"150","market_area_1_dscr":"1E Ryon, Irvington, Lindale Areas","year_improved":1948,"building_area":1008.0,"land_area":5500.0,"acreage":0.1263,"land_val":211750.0,"bld_val":21084.0,"x_features_val":0.0,"assessed_val":232834.0,"tot_appr_val":232834.0,"tot_mkt_val":232834.0,"new_construction_val":0.0,"protested":"Y","legal_description":"LT 17 BLK 48 IRVINGTON"},"buildings":[{"acct":"0211770480017","bld_num":1,"property_use_cd":"A1","structure_desc":"Residential","year_built":1948,"effective_year":1948,"im_sq_ft":1008.0,"act_ar":1824.0,"gross_ar":1824.0,"base_ar":1008.0}],"ownership_history":[{"acct":"0211770480017","owner_name":"PUENTE ROLAND","site_address":"4023 EDISON ST"}],"permits":[{"acct":"0211770480017","status":"C","description":"HCHA - MINOR","permit_type":"50","permit_type_desc":"Disaster Review","yr":2009}],"mls_listings":[],"valuation":{"method":"ZHVI-adjusted MLS comps","window_months":12,"sqft_band_pct":25,"lot_band_applied":true,"year_band_applied":true,"sqft_used":1008,"comp_count":38,"ppsf_low":249,"ppsf_mid":349,"ppsf_high":473,"est_low":251483,"est_mid":351549,"est_high":476956,"spread_pct":64,"confidence":"low","zhvi_as_of":"2026-04-30"}}