{"hcad":{"acct":"0211820640015","site_address":"4415 CETTI ST","site_address_norm":"4415 CETTI ST","zip_code":"77009","state_class":"A1","school_dist":"01","neighborhood_code":"7050.00","neighborhood_grp":"1541","market_area_1":"150","market_area_1_dscr":"1E Ryon, Irvington, Lindale Areas","year_improved":1955,"building_area":1754.0,"land_area":6820.0,"acreage":0.1566,"land_val":237160.0,"bld_val":98331.0,"x_features_val":2083.0,"assessed_val":337574.0,"tot_appr_val":337574.0,"tot_mkt_val":337574.0,"new_construction_val":0.0,"protested":"N","legal_description":"TRS 15 & 16A BLK 64 IRVINGTON"},"buildings":[{"acct":"0211820640015","bld_num":1,"property_use_cd":"A1","structure_desc":"Residential","year_built":1955,"effective_year":1955,"im_sq_ft":1754.0,"act_ar":1874.0,"gross_ar":1874.0,"base_ar":1754.0}],"ownership_history":[],"permits":[],"mls_listings":[],"valuation":{"method":"ZHVI-adjusted MLS comps","window_months":12,"sqft_band_pct":25,"lot_band_applied":true,"year_band_applied":true,"sqft_used":1754,"comp_count":68,"ppsf_low":208,"ppsf_mid":271,"ppsf_high":392,"est_low":364621,"est_mid":475345,"est_high":688359,"zhvi_as_of":"2026-04-30"}}