{"hcad":{"acct":"0201260000026","site_address":"447 W 16TH ST","site_address_norm":"447 W 16TH ST","zip_code":"77008","state_class":"A1","school_dist":"01","neighborhood_code":"8304.00","neighborhood_grp":"1639","market_area_1":"161","market_area_1_dscr":"1F Heights, Brooksmith, Norhill Areas","year_improved":2022,"building_area":4518.0,"land_area":13600.0,"acreage":0.3122,"land_val":1292000.0,"bld_val":1197700.0,"x_features_val":0.0,"assessed_val":2489700.0,"tot_appr_val":2489700.0,"tot_mkt_val":2489700.0,"new_construction_val":0.0,"protested":"Y","legal_description":"LTS 26 27 28 & 29 BLK 130 HOUSTON HEIGHTS"},"buildings":[{"acct":"0201260000026","bld_num":1,"property_use_cd":"A1","structure_desc":"Residential","year_built":2022,"effective_year":2022,"im_sq_ft":3998.0,"act_ar":6016.0,"gross_ar":6016.0,"base_ar":3998.0},{"acct":"0201260000026","bld_num":2,"property_use_cd":"A1","structure_desc":"Residential","year_built":2022,"effective_year":2022,"im_sq_ft":520.0,"act_ar":520.0,"gross_ar":520.0,"base_ar":520.0}],"ownership_history":[],"permits":[{"acct":"0201260000026","status":"C","description":"Subareas (581-588F), Rmdl","permit_type":"11","permit_type_desc":"Additions or Remodeling","yr":2004},{"acct":"0201260000026","status":"C","description":"DEMO RES/ SEWER DISC","permit_type":"13","permit_type_desc":"Residential Demolition","yr":2023},{"acct":"0201260000026","status":"C","description":"S.F. RES W/ATT GAR AND POOL HOUSE(1-1-5-R3-B) 12 I","permit_type":"10","permit_type_desc":"New Dwelling - permit","yr":2025},{"acct":"0201260000026","status":"C","description":"ONE-STOP NEW, SWIMMING POOL","permit_type":"07","permit_type_desc":"Extra Features (OB&Y)","yr":2024},{"acct":"0201260000026","status":"C","description":"ONE-STOP SOLAR PANEL, SINGLE FAMILY RESIDENTIAL","permit_type":"11","permit_type_desc":"Additions or Remodeling","yr":2025}],"mls_listings":[],"valuation":{"method":"ZHVI-adjusted MLS comps","window_months":30,"sqft_band_pct":25,"year_band_applied":true,"sqft_used":4518,"comp_count":154,"ppsf_low":324,"ppsf_mid":383,"ppsf_high":437,"est_low":1463612,"est_mid":1730141,"est_high":1973603,"zhvi_as_of":"2026-04-30"}}