{"hcad":{"acct":"0350810210018","site_address":"609 E 27TH ST","site_address_norm":"609 E 27TH ST","zip_code":"77008","state_class":"A1","school_dist":"01","neighborhood_code":"8305.00","neighborhood_grp":"1640","market_area_1":"161","market_area_1_dscr":"1F Heights, Brooksmith, Norhill Areas","year_improved":2003,"building_area":2648.0,"land_area":4200.0,"acreage":0.0964,"land_val":357000.0,"bld_val":452359.0,"x_features_val":10083.0,"assessed_val":819442.0,"tot_appr_val":819442.0,"tot_mkt_val":819442.0,"new_construction_val":0.0,"protested":"Y","legal_description":"LT 18 BLK 21 SUNSET HEIGHTS PAR AMEND 2"},"buildings":[{"acct":"0350810210018","bld_num":1,"property_use_cd":"A1","structure_desc":"Residential","year_built":2003,"effective_year":2003,"im_sq_ft":2648.0,"act_ar":2912.0,"gross_ar":2912.0,"base_ar":2648.0}],"ownership_history":[],"permits":[{"acct":"0350810210018","status":"C","description":"New Dwelling - permit","permit_type":"10","permit_type_desc":"New Dwelling - permit","yr":2005},{"acct":"0350810210018","status":"C","description":"30% F.D.RESIDENTIAL FIRE REPAIRS PER SPEC LIST REP","permit_type":"16","permit_type_desc":"Fire Reports","yr":2009}],"mls_listings":[],"valuation":{"method":"ZHVI-adjusted MLS comps","window_months":12,"sqft_band_pct":25,"lot_band_applied":true,"year_band_applied":true,"sqft_used":2648,"comp_count":189,"ppsf_low":255,"ppsf_mid":293,"ppsf_high":345,"est_low":674508,"est_mid":774720,"est_high":914836,"zhvi_as_of":"2026-04-30"}}