{"hcad":{"acct":"0222190000013","site_address":"611 LEVERKUHN ST","site_address_norm":"611 LEVERKUHN ST","zip_code":"77007","state_class":"A1","school_dist":"01","neighborhood_code":"8307.11","neighborhood_grp":"1623","market_area_1":"160","market_area_1_dscr":"1F Lazybrook, Timbergrove, Washington Corridor","year_improved":2000,"building_area":1760.0,"land_area":1350.0,"acreage":0.031,"protested":"N","legal_description":"TR 10B BLK 3 LEVERKUHN"},"buildings":[{"acct":"0222190000013","bld_num":1,"property_use_cd":"A1","structure_desc":"Residential","year_built":2000,"effective_year":2000,"im_sq_ft":1760.0,"act_ar":2299.0,"gross_ar":2299.0,"base_ar":1760.0}],"ownership_history":[],"permits":[],"mls_listings":[{"mls_number":"23994210","status":"Sold","property_type":"Townhouse/Condo","list_price":379997.0,"close_price":379900.0,"list_date":"2022-08-06","close_date":"2022-09-12","dom":13,"cdom":13,"bedrooms":2,"baths_full":2,"baths_half":1,"building_sqft":1890.0,"year_built":2000}],"valuation":{"method":"ZHVI-adjusted MLS comps","window_months":30,"sqft_band_pct":25,"year_band_applied":true,"sqft_used":1760,"comp_count":527,"ppsf_low":203,"ppsf_mid":223,"ppsf_high":248,"est_low":357591,"est_mid":392239,"est_high":436180,"zhvi_as_of":"2026-04-30"}}