{"hcad":{"acct":"0812470000009","site_address":"6403 WISTER LN","site_address_norm":"6403 WISTER LANE","zip_code":"77008","owner_name":"BERRY CHRISTIAN A","state_class":"A1","school_dist":"01","neighborhood_code":"8301.09","neighborhood_grp":"1613","market_area_1":"160","market_area_1_dscr":"1F Lazybrook, Timbergrove, Washington Corridor","year_improved":1955,"building_area":1444.0,"land_area":8710.0,"acreage":0.2,"land_val":437525.0,"bld_val":103166.0,"x_features_val":27219.0,"assessed_val":567910.0,"tot_appr_val":530237.0,"tot_mkt_val":567910.0,"new_construction_val":0.0,"protested":"Y","legal_description":"LT 9 BLK 37 TIMBERGROVE MANOR SEC 6"},"buildings":[{"acct":"0812470000009","bld_num":1,"property_use_cd":"A1","structure_desc":"Residential","year_built":1955,"effective_year":1955,"year_remodeled":2005,"im_sq_ft":1444.0,"act_ar":1864.0,"gross_ar":1864.0,"base_ar":1444.0}],"ownership_history":[{"acct":"0812470000009","owner_name":"BERRY CHRISTIAN A","site_address":"6403 WISTER LN"}],"permits":[{"acct":"0812470000009","status":"C","description":"NEW RESIDENTIAL SWIMMING POOL W/SPA 2021 IRC 2021","permit_type":"07","permit_type_desc":"Extra Features (OB&Y)","yr":2025},{"acct":"0812470000009","status":"C","description":"RESIDENTIAL PATIO COVER WITH STORAGE SHED ADDITION","permit_type":"07","permit_type_desc":"Extra Features (OB&Y)","yr":2025}],"mls_listings":[],"valuation":{"method":"ZHVI-adjusted MLS comps","window_months":12,"sqft_band_pct":15,"lot_band_applied":true,"year_band_applied":true,"sqft_used":1444,"comp_count":29,"ppsf_low":333,"ppsf_mid":369,"ppsf_high":412,"est_low":480141,"est_mid":533374,"est_high":594400,"zhvi_as_of":"2026-04-30"}}