{"hcad":{"acct":"1442060010001","site_address":"725 E 8TH ST","site_address_norm":"725 E 8TH STREET","zip_code":"77007","owner_name":"CHRISTIAN CHAD & ASHLEY","state_class":"A1","school_dist":"01","neighborhood_code":"8304.09","neighborhood_grp":"1621","market_area_1":"161","market_area_1_dscr":"1F Heights, Brooksmith, Norhill Areas","year_improved":2018,"building_area":4534.0,"land_area":9375.0,"acreage":0.2152,"land_val":843750.0,"bld_val":1717484.0,"x_features_val":46210.0,"assessed_val":2607444.0,"tot_appr_val":2501529.0,"tot_mkt_val":2607444.0,"new_construction_val":0.0,"protested":"Y","legal_description":"LT 1 BLK 1 EAST 8TH ESTATES"},"buildings":[{"acct":"1442060010001","bld_num":1,"property_use_cd":"A1","structure_desc":"Residential","year_built":2018,"effective_year":2018,"im_sq_ft":4534.0,"act_ar":6270.0,"gross_ar":6270.0,"base_ar":4534.0}],"ownership_history":[{"acct":"1442060010001","owner_name":"CHRISTIAN CHAD & ASHLEY","site_address":"725 E 8TH ST"}],"permits":[],"mls_listings":[],"valuation":{"method":"ZHVI-adjusted MLS comps","window_months":12,"sqft_band_pct":15,"lot_band_applied":true,"year_band_applied":true,"sqft_used":4534,"comp_count":16,"ppsf_low":386,"ppsf_mid":440,"ppsf_high":477,"est_low":1752290,"est_mid":1992997,"est_high":2164649,"zhvi_as_of":"2026-04-30"}}