{"hcad":{"acct":"1481460020004","site_address":"737 W 21ST ST A","site_address_norm":"737 W 21ST ST A","zip_code":"77008","state_class":"A1","school_dist":"01","neighborhood_code":"8305.07","neighborhood_grp":"1639","market_area_1":"161","market_area_1_dscr":"1F Heights, Brooksmith, Norhill Areas","year_improved":2025,"building_area":1914.0,"land_area":0.0,"acreage":0.0,"protested":"N","legal_description":"LT 4 BLK 1 GARDEN HEIGHTS LANDING R/P"},"buildings":[{"acct":"1481460020004","bld_num":1,"property_use_cd":"A1","structure_desc":"Residential","year_built":2025,"effective_year":2025,"im_sq_ft":1914.0,"act_ar":2522.0,"gross_ar":2522.0,"base_ar":1914.0}],"ownership_history":[],"permits":[{"acct":"1481460020004","status":"M","description":"S.F. RES. W/ATT. GARAGE (1-3-5-R3-B) 21 IRC/21 IEC","permit_type":"10","permit_type_desc":"New Dwelling - permit","yr":2027},{"acct":"1481460020004","status":"C","description":"DUPLEX RES. W/ATT. GARAGE (1-3-5-R3-B) 21 IRC/21 I","permit_type":"10","permit_type_desc":"New Dwelling - permit","yr":2026}],"mls_listings":[]}