{"hcad":{"acct":"1415370010055","site_address":"749 STRAWBERRY PINES CT","site_address_norm":"749 STRAWBERRY PINES COURT","zip_code":"77009","owner_name":"FR EAST HEIGHTS LLC","state_class":"A1","school_dist":"01","neighborhood_code":"8305.15","neighborhood_grp":"1657","market_area_1":"161","market_area_1_dscr":"1F Heights, Brooksmith, Norhill Areas","year_improved":2021,"building_area":1572.0,"land_area":2093.0,"acreage":0.048,"protested":"Y","legal_description":"LT 55 BLK 1 (PR YR IMPS 2022*1415370010094) EAST HEIGHTS AT AIRLINE"},"buildings":[{"acct":"1415370010055","bld_num":1,"property_use_cd":"A1","structure_desc":"Residential","year_built":2021,"effective_year":2021,"im_sq_ft":1572.0,"act_ar":1992.0,"gross_ar":1992.0,"base_ar":1572.0}],"ownership_history":[{"acct":"1415370010055","owner_name":"FR EAST HEIGHTS LLC","site_address":"749 STRAWBERRY PINES CT"}],"permits":[{"acct":"1415370010055","status":"C","description":"NEW DWG","permit_type":"09","permit_type_desc":"New Dwelling - no permit","yr":2022}],"mls_listings":[],"valuation":{"method":"ZHVI-adjusted MLS comps","window_months":12,"sqft_band_pct":25,"lot_band_applied":true,"year_band_applied":true,"sqft_used":1572,"comp_count":53,"ppsf_low":192,"ppsf_mid":203,"ppsf_high":213,"est_low":302022,"est_mid":319620,"est_high":335412,"spread_pct":10,"confidence":"high","zhvi_as_of":"2026-04-30"}}