{"hcad":{"acct":"1226560010004","site_address":"925 W 25TH ST","site_address_norm":"925 W 25TH STREET","zip_code":"77008","owner_name":"CIZEK LAURA S","state_class":"A1","school_dist":"01","neighborhood_code":"8303.02","neighborhood_grp":"1644","market_area_1":"160","market_area_1_dscr":"1F Lazybrook, Timbergrove, Washington Corridor","year_improved":2002,"building_area":1350.0,"land_area":3158.0,"acreage":0.0725,"land_val":221060.0,"bld_val":166681.0,"x_features_val":5840.0,"assessed_val":393581.0,"tot_appr_val":393581.0,"tot_mkt_val":393581.0,"new_construction_val":0.0,"protested":"N","legal_description":"LT 4 BLK 1 COTTAGE PARK ESTATES"},"buildings":[{"acct":"1226560010004","bld_num":1,"property_use_cd":"A1","structure_desc":"Residential","year_built":2002,"effective_year":2002,"im_sq_ft":1350.0,"act_ar":1550.0,"gross_ar":1550.0,"base_ar":1350.0}],"ownership_history":[{"acct":"1226560010004","owner_name":"CIZEK LAURA S","site_address":"925 W 25TH ST"}],"permits":[{"acct":"1226560010004","status":"C","description":"New Dwelling - no permit","permit_type":"09","permit_type_desc":"New Dwelling - no permit","yr":2004},{"acct":"1226560010004","status":"C","description":"DEMO RES/SEWER DISC","permit_type":"12","permit_type_desc":"Repairs (Foundation / GM)","yr":2020}],"mls_listings":[{"mls_number":"54814647","status":"Sold","property_type":"Single-Family","list_price":450000.0,"close_price":450000.0,"list_date":"2024-09-05","close_date":"2024-10-04","dom":6,"cdom":6,"bedrooms":2,"baths_full":2,"baths_half":1,"building_sqft":1250.0,"year_built":2002}],"valuation":{"method":"segment-adjusted MLS comps","window_months":12,"sqft_band_pct":25,"lot_band_applied":true,"year_band_applied":true,"sqft_used":1350,"comp_count":7,"ppsf_low":253,"ppsf_mid":271,"ppsf_high":335,"est_low":341146,"est_mid":365485,"est_high":452377,"spread_pct":30,"confidence":"medium","index_as_of":"2026-04-01"}}